rads/__init__.py
rads/__version__.py
rads/constants.py
rads/datetime64util.py
rads/exceptions.py
rads/py.typed
rads/rpn.py
rads/typing.py
rads/utility.py
rads/config/__init__.py
rads/config/ast.py
rads/config/builders.py
rads/config/grammar.py
rads/config/loader.py
rads/config/py.typed
rads/config/text_parsers.py
rads/config/tree.py
rads/config/utility.py
rads/config/xml_parsers.py
rads/xml/__init__.py
rads/xml/base.py
rads/xml/etree.py
rads/xml/lxml.py
rads/xml/py.typed
rads/xml/utility.py
tests/__init__.py
tests/conftest.py
tests/test_datetime64util.py
tests/test_integration.py
tests/test_rpn.py
tests/test_utility.py
tests/config/__init__.py
tests/config/test_text_parsers.py
tests/config/test_tree.py
tests/config/test_utility.py
tests/xml/__init__.py
tests/xml/test_utility.py
rads-0.1.0.post0.dist-info/LICENSE
rads-0.1.0.post0.dist-info/METADATA
rads-0.1.0.post0.dist-info/WHEEL
rads-0.1.0.post0.dist-info/top_level.txt
rads-0.1.0.post0.dist-info/RECORD
