Metadata-Version: 2.1
Name: rads
Version: 0.1.0.post0
Summary: Python front end for the Radar Altimeter Database System.
Home-page: https://github.com/ccarocean/pyrads
Author: Michael R. Shannon
Author-email: mrshannon.aerospace@gmail.com
License: MIT
Platform: UNKNOWN
Classifier: Development Status :: 3 - Alpha
Classifier: Intended Audience :: Science/Research
Classifier: License :: OSI Approved :: MIT License
Classifier: Programming Language :: Python
Classifier: Programming Language :: Python :: 3
Classifier: Programming Language :: Python :: 3.6
Classifier: Programming Language :: Python :: 3.7
Classifier: Programming Language :: Python :: Implementation :: CPython
Classifier: Topic :: Database :: Front-Ends
Classifier: Topic :: Scientific/Engineering
Classifier: Topic :: Scientific/Engineering :: GIS
Classifier: Topic :: Software Development :: Libraries :: Python Modules
Requires-Python: >=3.6
Requires-Dist: appdirs
Requires-Dist: astropy
Requires-Dist: cached-property
Requires-Dist: cf-units (>=2.1.1)
Requires-Dist: dataclass-builder (>=1.2.0)
Requires-Dist: fortran-format-converter (>=0.1.3)
Requires-Dist: numpy (>=1.16.0)
Requires-Dist: regex
Requires-Dist: scipy
Requires-Dist: sortedcontainers
Requires-Dist: wrapt
Requires-Dist: yzal
Requires-Dist: dataclasses ; python_version == "3.6"
Provides-Extra: checks
Requires-Dist: flake8 (>=3.7.7) ; extra == 'checks'
Requires-Dist: flake8-bugbear ; extra == 'checks'
Requires-Dist: mypy ; extra == 'checks'
Requires-Dist: pydocstyle ; extra == 'checks'
Requires-Dist: typing-extensions ; extra == 'checks'
Provides-Extra: dev
Requires-Dist: black ; extra == 'dev'
Requires-Dist: isort ; extra == 'dev'
Requires-Dist: twine ; extra == 'dev'
Requires-Dist: flake8 (>=3.7.7) ; extra == 'dev'
Requires-Dist: flake8-bugbear ; extra == 'dev'
Requires-Dist: mypy ; extra == 'dev'
Requires-Dist: pydocstyle ; extra == 'dev'
Requires-Dist: typing-extensions ; extra == 'dev'
Requires-Dist: pytest ; extra == 'dev'
Requires-Dist: pytest-cov ; extra == 'dev'
Requires-Dist: pytest-mock ; extra == 'dev'
Requires-Dist: packaging ; extra == 'dev'
Requires-Dist: sphinx (>=1.7) ; extra == 'dev'
Requires-Dist: sphinxcontrib-apidoc ; extra == 'dev'
Provides-Extra: docs
Requires-Dist: packaging ; extra == 'docs'
Requires-Dist: sphinx (>=1.7) ; extra == 'docs'
Requires-Dist: sphinxcontrib-apidoc ; extra == 'docs'
Provides-Extra: lxml
Requires-Dist: lxml ; extra == 'lxml'
Provides-Extra: tests
Requires-Dist: pytest ; extra == 'tests'
Requires-Dist: pytest-cov ; extra == 'tests'
Requires-Dist: pytest-mock ; extra == 'tests'
